fedora_messaging/__init__.py
fedora_messaging/api.py
fedora_messaging/cli.py
fedora_messaging/config.py
fedora_messaging/example.py
fedora_messaging/exceptions.py
fedora_messaging/message.py
fedora_messaging/schema_utils.py
fedora_messaging/signals.py
fedora_messaging/testing.py
fedora_messaging/twisted/__init__.py
fedora_messaging/twisted/consumer.py
fedora_messaging/twisted/factory.py
fedora_messaging/twisted/monitor.py
fedora_messaging/twisted/protocol.py
fedora_messaging/twisted/service.py
fedora_messaging/twisted/stats.py
fedora_messaging-3.7.0.dist-info/LICENSE
fedora_messaging-3.7.0.dist-info/METADATA
fedora_messaging-3.7.0.dist-info/WHEEL
fedora_messaging-3.7.0.dist-info/entry_points.txt
fedora_messaging-3.7.0.dist-info/RECORD
