Metadata-Version: 2.1
Name: fedora_messaging
Version: 3.7.0
Summary: A set of tools for using Fedora's messaging infrastructure
Home-page: https://github.com/fedora-infra/fedora-messaging
License: GPLv2+
Keywords: fedora
Author: Fedora Infrastructure
Author-email: admin@fedoraproject.org
Maintainer: Fedora Infrastructure Team
Requires-Python: >=3.8.10,<4.0.0
Classifier: Development Status :: 5 - Production/Stable
Classifier: License :: OSI Approved :: GNU General Public License v2 or later (GPLv2+)
Classifier: License :: Other/Proprietary License
Classifier: Operating System :: POSIX :: Linux
Classifier: Programming Language :: Python :: 3
Classifier: Programming Language :: Python :: 3.9
Classifier: Programming Language :: Python :: 3.10
Classifier: Programming Language :: Python :: 3.11
Classifier: Programming Language :: Python :: 3.12
Classifier: Programming Language :: Python :: 3.13
Classifier: Programming Language :: Python :: 3.8
Requires-Dist: blinker (>=1.5,<2.0)
Requires-Dist: click (>=8.0.3,<9.0.0)
Requires-Dist: crochet (>=1.12.0)
Requires-Dist: jsonschema (>=3.2.0,<5.0.0)
Requires-Dist: pika (>=1.2.1,<2.0.0)
Requires-Dist: pyopenssl (>=21.0.0)
Requires-Dist: requests (>=2.5.0)
Requires-Dist: service-identity (>=21.1.0)
Requires-Dist: tomli (>=2.0.1,<3.0.0)
Requires-Dist: twisted (>=22.4.0)
Project-URL: Repository, https://github.com/fedora-infra/fedora-messaging
